{
    "pageTable": [
        {
            "title": "产品类型",
            "dataIndex": "",
            "type": "select",
            "enum": []
        },
        {
            "title": "厂区名",
            "dataIndex": "",
            "type": "select",
            "enum": []
        },
        {
            "title": "组焊类型",
            "dataIndex": "",
            "type": "select",
            "enum": []
        },
        {
            "title": "组焊加工车间",
            "dataIndex": "",
            "type": "select",
            "enum": []
        },
        {
            "title": "加工车间",
            "dataIndex": "",
            "type": "select",
            "enum": []
        }
    ]
}