{
    "baseColumn": [
        {
            "title": "领料编号",
            "dataIndex": "pickingNumber",
            "width": 120
        },
        {
            "title": "状态",
            "dataIndex": "stockStatusName",
            "width": 80
        },
        {
            "title": "最新状态变更时间",
            "dataIndex": "updateTime",
            "type": "date",
            "width": 120
        },
        {
            "title": "工程名称",
            "dataIndex": "projectName",
            "width": 80
        },
        {
            "title": "申请人",
            "dataIndex": "applyStaffName",
            "width": 80
        }
    ]
}