{
    "invoicingListHead": [
        {
            "title": "申请编号",
            "dataIndex": "invoicingCode"
        },
        {
            "title": "项目编号",
            "dataIndex": "projectCode"
        },
        {
            "title": "内部合同编号",
            "dataIndex": "contractCode"
        },
        {
            "title": "计划号",
            "dataIndex": "planCode"
        },
        {
            "title": "票面单位",
            "dataIndex": "ticketCompany"
        },
        {
            "title": "工程名称",
            "dataIndex": ""
        },
        {
            "title": "合计金额(元)",
            "dataIndex": "ticketMoney"
        },
        {
            "title": "合计重量(元/吨)",
            "dataIndex": "ticketWeight"
        },
        {
            "title": "业务经理",
            "dataIndex": "business"
        },
        {
            "title": "发票类型",
            "dataIndex": "ticketType"
        },
        {
            "title": "开票日期",
            "dataIndex": "ticketTime"
        },
        {
            "title": "是否已全开",
            "dataIndex": "isOpen"
        },
        {
            "title": "开票时合同状态",
            "dataIndex": "contractType"
        },
        {
            "title": "承诺回款时间",
            "dataIndex": "businessBackTime"
        },
        {
            "title": "承诺回款比例",
            "dataIndex": "backProportion"
        },
        {
            "title": "验收单",
            "dataIndex": "isCheck"
        },
        {
            "title": "合同单位",
            "dataIndex": "contractCompany"
        },
        {
            "title": "合同签订日期",
            "dataIndex": ""
        },
        {
            "title": "开票方式",
            "dataIndex": "openTicketType"
        },
        {
            "title": "开票依据",
            "dataIndex": "ticketBasis"
        },
        {
            "title": "最后发货日期",
            "dataIndex": "contractLastTime"
        },
        {
            "title": "开票次数",
            "dataIndex": "ticketCount"
        },
        {
            "title": "申请时间",
            "dataIndex": "createTime"
        },
        {
            "title": "制单",
            "dataIndex": ""
        },
        {
            "title": "制单时间",
            "dataIndex": ""
        },
        {
            "title": "状态",
            "dataIndex": "status"
        }
    ],
    "baseInfoHead": [
        {
            "title": "",
            "dataIndex": ""
        }
    ],
    "invoiceHead": []
}